StdTool/__init__.py
StdTool/setup.py
StdTool/torch.py
StdTool/iolib/__init__.py
StdTool/runlib/__init__.py
StdTool/runlib/asynchrony.py
StdTool/runlib/concur.py
StdTool/runlib/subp.py
StdTool/syslib/__init__.py
StdTool/syslib/console.py
StdTool/syslib/envs.py
StdTool/syslib/path.py
StdTool/syslib/string.py
StdTool/syslib/time.py
StdTool-0.1.5.dist-info/METADATA
StdTool-0.1.5.dist-info/WHEEL
StdTool-0.1.5.dist-info/top_level.txt
StdTool-0.1.5.dist-info/RECORD
